keysentinel/__init__.py
keysentinel/cli.py
keysentinel/config.py
keysentinel/decryption.py
keysentinel/encryption.py
keysentinel/exceptions.py
keysentinel/profiles.py
keysentinel/utils.py
keysentinel-0.2.6.dist-info/licenses/LICENSE
zero_trust/__init__.py
keysentinel-0.2.6.dist-info/METADATA
keysentinel-0.2.6.dist-info/WHEEL
keysentinel-0.2.6.dist-info/entry_points.txt
keysentinel-0.2.6.dist-info/top_level.txt
keysentinel-0.2.6.dist-info/RECORD
