Metadata-Version: 2.4
Name: keysentinel
Version: 0.2.6
Summary: Secure token management library for CLI tools, using two-layer encryption with local key and 1Password vault integration.
Author-email: Davi Guides <davi.guides@gmail.com>
License-Expression: MIT
Project-URL: Homepage, https://github.com/daviguides/keysentinel
Project-URL: Repository, https://github.com/daviguides/keysentinel
Classifier: Programming Language :: Python :: 3
Classifier: Programming Language :: Python :: 3.11
Classifier: Programming Language :: Python :: 3.12
Classifier: Operating System :: OS Independent
Classifier: Topic :: Security
Classifier: Topic :: Utilities
Classifier: Intended Audience :: Developers
Requires-Python: >=3.11
License-File: LICENSE
Requires-Dist: cryptography>=42.0.0
Requires-Dist: pyperclip>=1.9.0
Requires-Dist: typer>=0.15.2
Dynamic: license-file
